convunits/__init__.py
convunits/convert.py
convunits/definitions.py
convunits/errors.py
convunits/expression.py
convunits/models.py
convunits/unit_definitions/__init__.py
convunits/unit_definitions/acceleration.py
convunits/unit_definitions/angle.py
convunits/unit_definitions/angular_frequency.py
convunits/unit_definitions/api_gravity.py
convunits/unit_definitions/apparent_power.py
convunits/unit_definitions/area.py
convunits/unit_definitions/charge.py
convunits/unit_definitions/conductivity.py
convunits/unit_definitions/current.py
convunits/unit_definitions/density.py
convunits/unit_definitions/dogleg_severity.py
convunits/unit_definitions/each.py
convunits/unit_definitions/energy.py
convunits/unit_definitions/force.py
convunits/unit_definitions/frequency.py
convunits/unit_definitions/gamma_ray.py
convunits/unit_definitions/illuminance.py
convunits/unit_definitions/inverse_length.py
convunits/unit_definitions/inverse_resistivity.py
convunits/unit_definitions/length.py
convunits/unit_definitions/mass.py
convunits/unit_definitions/mass_flow_rate.py
convunits/unit_definitions/money.py
convunits/unit_definitions/money_per_energy.py
convunits/unit_definitions/pixels.py
convunits/unit_definitions/power.py
convunits/unit_definitions/pressure.py
convunits/unit_definitions/pressure_gradient.py
convunits/unit_definitions/productivity_index.py
convunits/unit_definitions/ratio.py
convunits/unit_definitions/reactive_energy.py
convunits/unit_definitions/reactive_power.py
convunits/unit_definitions/resistivity.py
convunits/unit_definitions/slowness.py
convunits/unit_definitions/temperature.py
convunits/unit_definitions/temperature_difference.py
convunits/unit_definitions/time.py
convunits/unit_definitions/torque.py
convunits/unit_definitions/unitless.py
convunits/unit_definitions/velocity.py
convunits/unit_definitions/voltage.py
convunits/unit_definitions/volume.py
convunits/unit_definitions/volume_ratio.py
convunits/unit_definitions/volumetric_flow_rate.py
convunits-0.0.1.dist-info/METADATA
convunits-0.0.1.dist-info/WHEEL
convunits-0.0.1.dist-info/top_level.txt
convunits-0.0.1.dist-info/RECORD
